toon_troubleshooter/__init__.py
toon_troubleshooter/main.py
toon_troubleshooter/prompts.py
toon_troubleshooter-2025.12.22090741.dist-info/METADATA
toon_troubleshooter-2025.12.22090741.dist-info/WHEEL
toon_troubleshooter-2025.12.22090741.dist-info/top_level.txt
toon_troubleshooter-2025.12.22090741.dist-info/RECORD
