Metadata-Version: 2.4
Name: toon-troubleshooter
Version: 2025.12.22090741
Summary: Toon-troubleshooter identifies and solves Cartoon Network viewing issues via user input and structured responses.
Author-email: toon-troubleshooter <hi@eugene.plus>
License: MIT
Project-URL: Homepage, https://github.com/chigwell/toon-troubleshooter
Requires-Python: >=3.9
Requires-Dist: langchain-llm7>=0.0.0
Requires-Dist: llmatch-messages>=0.0.0
Requires-Dist: langchain-core>=0.3.0
